onnx_ir/__init__.py
onnx_ir/_core.py
onnx_ir/_display.py
onnx_ir/_enums.py
onnx_ir/_graph_comparison.py
onnx_ir/_graph_containers.py
onnx_ir/_io.py
onnx_ir/_linked_list.py
onnx_ir/_metadata.py
onnx_ir/_name_authority.py
onnx_ir/_polyfill.py
onnx_ir/_protocols.py
onnx_ir/_tape.py
onnx_ir/_type_casting.py
onnx_ir/_version_utils.py
onnx_ir/convenience.py
onnx_ir/external_data.py
onnx_ir/py.typed
onnx_ir/serde.py
onnx_ir/tape.py
onnx_ir/tensor_adapters.py
onnx_ir/testing.py
onnx_ir/traversal.py
onnx_ir/_convenience/__init__.py
onnx_ir/_convenience/_constructors.py
onnx_ir/_thirdparty/asciichartpy.py
onnx_ir/passes/__init__.py
onnx_ir/passes/_pass_infra.py
onnx_ir/passes/common/__init__.py
onnx_ir/passes/common/_c_api_utils.py
onnx_ir/passes/common/clear_metadata_and_docstring.py
onnx_ir/passes/common/common_subexpression_elimination.py
onnx_ir/passes/common/constant_manipulation.py
onnx_ir/passes/common/identity_elimination.py
onnx_ir/passes/common/initializer_deduplication.py
onnx_ir/passes/common/inliner.py
onnx_ir/passes/common/naming.py
onnx_ir/passes/common/onnx_checker.py
onnx_ir/passes/common/output_fix.py
onnx_ir/passes/common/shape_inference.py
onnx_ir/passes/common/topological_sort.py
onnx_ir/passes/common/unused_removal.py
onnx_ir-0.1.13.dist-info/licenses/LICENSE
onnx_ir-0.1.13.dist-info/METADATA
onnx_ir-0.1.13.dist-info/WHEEL
onnx_ir-0.1.13.dist-info/top_level.txt
onnx_ir-0.1.13.dist-info/RECORD
