Metadata-Version: 2.4
Name: onnx-ir
Version: 0.1.13
Summary: Efficient in-memory representation for ONNX
Author-email: ONNX Contributors <onnx-technical-discuss@lists.lfaidata.foundation>
License-Expression: Apache-2.0
Project-URL: Homepage, https://onnx.ai/ir-py
Project-URL: Issues, https://github.com/onnx/ir-py/issues
Project-URL: Repository, https://github.com/onnx/ir-py
Classifier: Development Status :: 4 - Beta
Requires-Python: >=3.9
License-File: LICENSE
Requires-Dist: numpy
Requires-Dist: onnx>=1.16
Requires-Dist: typing_extensions>=4.10
Requires-Dist: ml_dtypes>=0.5.0
Dynamic: license-file
